{
    "末日浩劫": "https://movie.douban.com/subject/19976260/",
    "我是传奇": "https://movie.douban.com/subject/1820156/",
    "极度恐慌": "https://movie.douban.com/subject/1301419/",
    "惊变28天": "https://movie.douban.com/subject/1306421/",
    "十二猴子": "https://movie.douban.com/subject/1298744/",
    "蒙上你的眼": "https://movie.douban.com/subject/27092648/",
    "传染病": "https://movie.douban.com/subject/4301043/",
    "流感": "https://movie.douban.com/subject/10432911/",
    "铁线虫入侵": "https://movie.douban.com/subject/6839145/",
    "釜山行": "https://movie.douban.com/subject/25986180/",
    "僵尸世界大战": "https://movie.douban.com/subject/2132473/"
}